<?xml version="1.0" encoding="utf-8" ?>
<dwsync>
<file name="ds_forms.admin.js" server="ftp.oxysilver.eu/www/" local="129645612720000000" remote="129681844800000000" />
<file name="ds_forms.info" server="ftp.oxysilver.eu/www/" local="129645621320000000" remote="129681844800000000" />
<file name="ds_forms.install" server="ftp.oxysilver.eu/www/" local="129645612720000000" remote="129681844800000000" />
<file name="ds_forms.module" server="ftp.oxysilver.eu/www/" local="129645612720000000" remote="129681844800000000" />
<file name="ds_forms.admin.js" server="C:/wamp/www/oxysilver/" local="129645612720000000" remote="129645612720000000" />
<file name="ds_forms.info" server="C:/wamp/www/oxysilver/" local="129645621320000000" remote="129645621320000000" />
<file name="ds_forms.install" server="C:/wamp/www/oxysilver/" local="129645612720000000" remote="129645612720000000" />
<file name="ds_forms.module" server="C:/wamp/www/oxysilver/" local="129645612720000000" remote="129645612720000000" />
<file name="ds_forms.admin.js" server="C:/wamp/www/monster tuning/" local="129645612720000000" remote="129645612720000000" />
<file name="ds_forms.info" server="C:/wamp/www/monster tuning/" local="129645621320000000" remote="129645621320000000" />
<file name="ds_forms.install" server="C:/wamp/www/monster tuning/" local="129645612720000000" remote="129645612720000000" />
<file name="ds_forms.module" server="C:/wamp/www/monster tuning/" local="129645612720000000" remote="129645612720000000" />
<file name="ds_forms.admin.js" server="213.175.214.220/www/" local="129645612720000000" remote="129742557000000000" />
<file name="ds_forms.info" server="213.175.214.220/www/" local="129645621320000000" remote="129742557000000000" />
<file name="ds_forms.install" server="213.175.214.220/www/" local="129645612720000000" remote="129742557000000000" />
<file name="ds_forms.module" server="213.175.214.220/www/" local="129645612720000000" remote="129742557000000000" />
</dwsync>